streamlit_chitchat/__init__.py
streamlit_chitchat/streamlit_chitchat/__init__.py
streamlit_chitchat/streamlit_chitchat/chitchat.py
streamlit_chitchat/streamlit_chitchat/data.py
streamlit_chitchat/streamlit_chitchat/utils.py
streamlit_chitchat/tests/__init__.py
streamlit_chitchat/tests/main.py
streamlit_chitchat-0.1.7.dist-info/METADATA
streamlit_chitchat-0.1.7.dist-info/WHEEL
streamlit_chitchat-0.1.7.dist-info/RECORD
