Metadata-Version: 2.1
Name: streamlit-chitchat
Version: 0.1.7
Summary: 
Author: k4144
Author-email: github.k4144@gmail.com
Requires-Python: >=3.9,<4.0
Classifier: Programming Language :: Python :: 3
Classifier: Programming Language :: Python :: 3.9
Classifier: Programming Language :: Python :: 3.10
Classifier: Programming Language :: Python :: 3.11
